Workbook

Sheet Sheet1
A1: 最终用户 | B1: siebel编码 | C1: CRM销售域账号 | D1: 销售部门 | E1: 是否规上 | F1: 产品宽度合计 | G1: IPC | H1: 球机 | I1: 专用摄像机 | J1: 服务器 | K1: 网络产品 | L1: PC产品 | M1: NVR | N1: 存储 | O1: LED与拼控 | P1: LCD与解码 | Q1: 智能交通 | R1: 移动终端产品 | S1: 出入口停车 | T1: 门禁 | U1: 对讲 | V1: 人员通道 | W1: 报警 | X1: 音频产品 | Y1: 传感产品 | Z1: 智慧屏与视频会议 | AA1: 通用软件 | AB1: 行业软件 | AC1: 基础软件 | AD1: 新业务（热成像/睿影/消防等） | AE1: 网络安全 | AF1: 综合布线与机柜机房 | AG1: 智能计算
A2: 光大环保（中国）有限公司 | B2: 1-1GY7K51 | C2: 陶文杰 | D2: =VLOOKUP(C2,[1]销售对应表!$C:$J,5,0) -> 政府行业组 | E2: 是 | F2: =SUM(G2:AG2) -> 11 | G2: 1 | H2: 1 | I2: 1 | J2: 0 | K2: 1 | L2: 0 | M2: 1 | N2: 1 | O2: 1 | P2: 0 | Q2: 1 | R2: 0 | S2: 1 | T2: 1 | U2: 0 | V2: 0 | W2: 0 | X2: 0 | Y2: 0 | Z2: 0 | AA2: 0 | AB2: 0 | AC2: 0 | AD2: 0 | AE2: 0 | AF2: 1 | AG2: 0
A3: 东江环保股份有限公司 | B3: 1-DRS-2933862 | C3: 陶文杰 | D3: =VLOOKUP(C3,[1]销售对应表!$C:$J,5,0) -> 政府行业组 | E3: 是 | F3: =SUM(G3:AG3) -> 7 | G3: 1 | H3: 1 | I3: 0 | J3: 1 | K3: 0 | L3: 0 | M3: 0 | N3: 1 | O3: 0 | P3: 1 | Q3: 0 | R3: 0 | S3: 0 | T3: 0 | U3: 0 | V3: 0 | W3: 0 | X3: 0 | Y3: 0 | Z3: 0 | AA3: 1 | AB3: 0 | AC3: 1 | AD3: 0 | AE3: 0 | AF3: 0 | AG3: 0
A4: 深圳市生态环境局 | B4: 1-3TCI8KI | C4: 陶文杰 | D4: =VLOOKUP(C4,[1]销售对应表!$C:$J,5,0) -> 政府行业组 | E4: 否 | F4: =SUM(G4:AG4) -> 8 | G4: 1 | H4: 1 | I4: 0 | J4: 0 | K4: 0 | L4: 0 | M4: 1 | N4: 0 | O4: 0 | P4: 0 | Q4: 0 | R4: 0 | S4: 0 | T4: 1 | U4: 0 | V4: 0 | W4: 0 | X4: 1 | Y4: 0 | Z4: 0 | AA4: 1 | AB4: 0 | AC4: 0 | AD4: 1 | AE4: 0 | AF4: 0 | AG4: 1
A5: 中国联合网络通信有限公司深圳市分公司 | B5: 1-1EEGHD1 | C5: 陶文杰 | D5: =VLOOKUP(C5,[1]销售对应表!$C:$J,5,0) -> 政府行业组 | E5: 是 | F5: =SUM(G5:AG5) -> 7 | G5: 1 | H5: 0 | I5: 0 | J5: 0 | K5: 0 | L5: 0 | M5: 0 | N5: 0 | O5: 0 | P5: 1 | Q5: 0 | R5: 0 | S5: 0 | T5: 1 | U5: 0 | V5: 0 | W5: 0 | X5: 1 | Y5: 0 | Z5: 0 | AA5: 1 | AB5: 0 | AC5: 1 | AD5: 1 | AE5: 0 | AF5: 0 | AG5: 0
A6: 深圳市宝安区城市管理和综合执法局 | B6: 1-1XMZU1B | C6: 陶文杰 | D6: =VLOOKUP(C6,[1]销售对应表!$C:$J,5,0) -> 政府行业组 | E6: 是 | F6: =SUM(G6:AG6) -> 7 | G6: 1 | H6: 0 | I6: 0 | J6: 0 | K6: 1 | L6: 0 | M6: 0 | N6: 0 | O6: 0 | P6: 0 | Q6: 0 | R6: 0 | S6: 0 | T6: 1 | U6: 0 | V6: 0 | W6: 0 | X6: 0 | Y6: 0 | Z6: 0 | AA6: 1 | AB6: 1 | AC6: 1 | AD6: 1 | AE6: 0 | AF6: 0 | AG6: 0
A7: 深圳市宝安区松岗街道办事处 | B7: 1-DRFT-2985630 | C7: 陶文杰 | D7: =VLOOKUP(C7,[1]销售对应表!$C:$J,5,0) -> 政府行业组 | E7: 是 | F7: =SUM(G7:AG7) -> 7 | G7: 0 | H7: 1 | I7: 0 | J7: 0 | K7: 0 | L7: 1 | M7: 1 | N7: 1 | O7: 0 | P7: 1 | Q7: 0 | R7: 0 | S7: 0 | T7: 0 | U7: 1 | V7: 0 | W7: 0 | X7: 0 | Y7: 0 | Z7: 0 | AA7: 0 | AB7: 0 | AC7: 0 | AD7: 0 | AE7: 0 | AF7: 0 | AG7: 1
A8: 深圳市福田区城市管理和综合执法局 | B8: 1-22NTEEU | C8: 陶文杰 | D8: =VLOOKUP(C8,[1]销售对应表!$C:$J,5,0) -> 政府行业组 | E8: 是 | F8: =SUM(G8:AG8) -> 5 | G8: 1 | H8: 1 | I8: 0 | J8: 0 | K8: 1 | L8: 0 | M8: 0 | N8: 0 | O8: 0 | P8: 0 | Q8: 0 | R8: 0 | S8: 0 | T8: 0 | U8: 0 | V8: 0 | W8: 0 | X8: 0 | Y8: 0 | Z8: 0 | AA8: 1 | AB8: 0 | AC8: 0 | AD8: 0 | AE8: 0 | AF8: 0 | AG8: 1
A9: 深圳市南山区城市管理局 | B9: 1-DRS-2936417 | C9: 陶文杰 | D9: =VLOOKUP(C9,[1]销售对应表!$C:$J,5,0) -> 政府行业组 | E9: 是 | F9: =SUM(G9:AG9) -> 6 | G9: 1 | H9: 0 | I9: 0 | J9: 0 | K9: 1 | L9: 0 | M9: 0 | N9: 0 | O9: 0 | P9: 1 | Q9: 0 | R9: 0 | S9: 0 | T9: 1 | U9: 0 | V9: 0 | W9: 0 | X9: 0 | Y9: 0 | Z9: 0 | AA9: 0 | AB9: 1 | AC9: 0 | AD9: 1 | AE9: 0 | AF9: 0 | AG9: 0
A10: 深圳市生态环境局龙岗管理局 | B10: 1-4O2ANDW | C10: 陶文杰 | D10: =VLOOKUP(C10,[1]销售对应表!$C:$J,5,0) -> 政府行业组 | E10: 是 | F10: =SUM(G10:AG10) -> 4 | G10: 1 | H10: 1 | I10: 0 | J10: 0 | K10: 0 | L10: 0 | M10: 1 | N10: 0 | O10: 0 | P10: 0 | Q10: 0 | R10: 0 | S10: 0 | T10: 1 | U10: 0 | V10: 0 | W10: 0 | X10: 0 | Y10: 0 | Z10: 0 | AA10: 0 | AB10: 0 | AC10: 0 | AD10: 0 | AE10: 0 | AF10: 0 | AG10: 0
A11: 深圳市宝安区新安街道办事处 | B11: 1-1W8IBND | C11: 陶文杰 | D11: =VLOOKUP(C11,[1]销售对应表!$C:$J,5,0) -> 政府行业组 | E11: 否 | F11: =SUM(G11:AG11) -> 3 | G11: 0 | H11: 1 | I11: 1 | J11: 0 | K11: 1 | L11: 0 | M11: 0 | N11: 0 | O11: 0 | P11: 0 | Q11: 0 | R11: 0 | S11: 0 | T11: 0 | U11: 0 | V11: 0 | W11: 0 | X11: 0 | Y11: 0 | Z11: 0 | AA11: 0 | AB11: 0 | AC11: 0 | AD11: 0 | AE11: 0 | AF11: 0 | AG11: 0
A12: 深圳市龙岗区城市管理局（深圳市龙岗区城市管理行政执法局） | B12: 1-229SRQZ | C12: 陶文杰 | D12: =VLOOKUP(C12,[1]销售对应表!$C:$J,5,0) -> 政府行业组 | E12: 是 | F12: =SUM(G12:AG12) -> 4 | G12: 1 | H12: 1 | I12: 0 | J12: 0 | K12: 0 | L12: 0 | M12: 0 | N12: 0 | O12: 0 | P12: 0 | Q12: 0 | R12: 0 | S12: 0 | T12: 0 | U12: 1 | V12: 0 | W12: 0 | X12: 0 | Y12: 0 | Z12: 0 | AA12: 0 | AB12: 0 | AC12: 0 | AD12: 1 | AE12: 0 | AF12: 0 | AG12: 0
A13: 深圳市罗湖区城市管理和综合执法局 | B13: 1-4ESDREP | C13: 陶文杰 | D13: =VLOOKUP(C13,[1]销售对应表!$C:$J,5,0) -> 政府行业组 | E13: 否 | F13: =SUM(G13:AG13) -> 3 | G13: 1 | H13: 0 | I13: 0 | J13: 0 | K13: 0 | L13: 0 | M13: 0 | N13: 0 | O13: 0 | P13: 0 | Q13: 0 | R13: 0 | S13: 0 | T13: 0 | U13: 1 | V13: 0 | W13: 0 | X13: 0 | Y13: 0 | Z13: 0 | AA13: 1 | AB13: 0 | AC13: 0 | AD13: 0 | AE13: 0 | AF13: 0 | AG13: 0
... A110: 深圳市智慧城市科技发展集团有限公司 | B110: 1-3V6FWWV | C110: 廖贝贝 | D110: =VLOOKUP(C110,[1]销售对应表!$C:$J,5,0) -> 政府行业组 | E110: 否 | F110: =SUM(G110:AG110) -> 1 | G110: 0 | H110: 0 | I110: 0 | J110: 0 | K110: 1 | L110: 0 | M110: 0 | N110: 0 | O110: 0 | P110: 0 | Q110: 0 | R110: 0 | S110: 0 | T110: 0 | U110: 0 | V110: 0 | W110: 0 | X110: 0 | Y110: 0 | Z110: 0 | AA110: 0 | AB110: 0 | AC110: 0 | AD110: 0 | AE110: 0 | AF110: 0 | AG110: 0
A111: 深圳市龙岗区教育局 | B111: 1-1P0O8 | C111: 张岩27 | D111: 教育教学 | E111: 是 | F111: =SUM(G111:AG111) -> 17 | G111: 1 | H111: 1 | I111: 0 | J111: 1 | K111: 1 | L111: 1 | M111: 1 | N111: 0 | O111: 1 | P111: 1 | Q111: 0 | R111: 0 | S111: 1 | T111: 1 | U111: 0 | V111: 1 | W111: 1 | X111: 0 | Y111: 0 | Z111: 0 | AA111: 0 | AB111: 1 | AC111: 0 | AD111: 1 | AE111: 1 | AF111: 1 | AG111: 1
A112: 深圳市福田区教育局 | B112: 1-HQ-1044230 | C112: 张岩27 | D112: 教育教学 | E112: 是 | F112: =SUM(G112:AG112) -> 14 | G112: 1 | H112: 1 | I112: 0 | J112: 0 | K112: 1 | L112: 1 | M112: 1 | N112: 0 | O112: 1 | P112: 1 | Q112: 0 | R112: 0 | S112: 0 | T112: 1 | U112: 0 | V112: 0 | W112: 1 | X112: 1 | Y112: 0 | Z112: 0 | AA112: 1 | AB112: 1 | AC112: 0 | AD112: 1 | AE112: 0 | AF112: 1 | AG112: 0
A113: 深圳市福田区北京大学附属中学深圳学校（集团）黄埔学校 | B113: 1-1ELONLH | C113: 张岩27 | D113: 教育教学 | E113: 是 | F113: =SUM(G113:AG113) -> 10 | G113: 1 | H113: 0 | I113: 0 | J113: 1 | K113: 1 | L113: 1 | M113: 1 | N113: 0 | O113: 0 | P113: 1 | Q113: 0 | R113: 0 | S113: 0 | T113: 1 | U113: 0 | V113: 0 | W113: 0 | X113: 1 | Y113: 0 | Z113: 0 | AA113: 0 | AB113: 0 | AC113: 0 | AD113: 1 | AE113: 0 | AF113: 1 | AG113: 0
A114: 深圳市罗湖区滨河实验中学 | B114: 1-4SBHDK8 | C114: 张岩27 | D114: 教育教学 | E114: 是 | F114: =SUM(G114:AG114) -> 10 | G114: 0 | H114: 1 | I114: 0 | J114: 1 | K114: 0 | L114: 1 | M114: 0 | N114: 1 | O114: 1 | P114: 1 | Q114: 0 | R114: 0 | S114: 0 | T114: 0 | U114: 0 | V114: 0 | W114: 1 | X114: 0 | Y114: 0 | Z114: 0 | AA114: 1 | AB114: 0 | AC114: 0 | AD114: 1 | AE114: 0 | AF114: 1 | AG114: 0
A115: 深圳市罗湖区教育局 | B115: 1-HQ-1041962 | C115: 张岩27 | D115: 教育教学 | E115: 是 | F115: =SUM(G115:AG115) -> 9 | G115: 1 | H115: 0 | I115: 0 | J115: 1 | K115: 0 | L115: 0 | M115: 1 | N115: 0 | O115: 1 | P115: 1 | Q115: 0 | R115: 0 | S115: 0 | T115: 0 | U115: 1 | V115: 0 | W115: 0 | X115: 0 | Y115: 0 | Z115: 0 | AA115: 1 | AB115: 1 | AC115: 0 | AD115: 0 | AE115: 0 | AF115: 1 | AG115: 0
A116: 深圳市桂园中学 | B116: 1-DRF-2819418 | C116: 张岩27 | D116: 教育教学 | E116: 是 | F116: =SUM(G116:AG116) -> 9 | G116: 1 | H116: 1 | I116: 0 | J116: 0 | K116: 0 | L116: 1 | M116: 1 | N116: 1 | O116: 0 | P116: 1 | Q116: 0 | R116: 0 | S116: 0 | T116: 1 | U116: 0 | V116: 0 | W116: 0 | X116: 0 | Y116: 0 | Z116: 1 | AA116: 0 | AB116: 0 | AC116: 0 | AD116: 0 | AE116: 0 | AF116: 1 | AG116: 0
A117: 深圳市螺岭外国语实验学校 | B117: 1-DRF-2811593 | C117: 张岩27 | D117: 教育教学 | E117: 是 | F117: =SUM(G117:AG117) -> 8 | G117: 1 | H117: 0 | I117: 0 | J117: 1 | K117: 0 | L117: 0 | M117: 1 | N117: 0 | O117: 0 | P117: 1 | Q117: 0 | R117: 0 | S117: 0 | T117: 1 | U117: 0 | V117: 0 | W117: 1 | X117: 0 | Y117: 0 | Z117: 0 | AA117: 0 | AB117: 1 | AC117: 0 | AD117: 0 | AE117: 0 | AF117: 1 | AG117: 0
A118: 深圳市翠园中学 | B118: 1-ALLON-3107116 | C118: 张岩27 | D118: 教育教学 | E118: 否 | F118: =SUM(G118:AG118) -> 8 | G118: 1 | H118: 1 | I118: 0 | J118: 1 | K118: 1 | L118: 0 | M118: 1 | N118: 0 | O118: 0 | P118: 1 | Q118: 0 | R118: 0 | S118: 0 | T118: 0 | U118: 0 | V118: 0 | W118: 0 | X118: 0 | Y118: 0 | Z118: 1 | AA118: 1 | AB118: 0 | AC118: 0 | AD118: 0 | AE118: 0 | AF118: 0 | AG118: 0
A119: 深圳市龙岗区龙城高级中学（深圳市龙岗区龙城高级中学（教育集团）） | B119: 1-6SA1YMT | C119: 张岩27 | D119: 教育教学 | E119: 是 | F119: =SUM(G119:AG119) -> 6 | G119: 1 | H119: 1 | I119: 0 | J119: 0 | K119: 1 | L119: 0 | M119: 1 | N119: 0 | O119: 0 | P119: 0 | Q119: 0 | R119: 0 | S119: 0 | T119: 0 | U119: 0 | V119: 0 | W119: 0 | X119: 0 | Y119: 0 | Z119: 0 | AA119: 0 | AB119: 1 | AC119: 0 | AD119: 1 | AE119: 0 | AF119: 0 | AG119: 0
A120: 深圳明德实验学校 | B120: 1-DRF-2814538 | C120: 张岩27 | D120: 教育教学 | E120: 是 | F120: =SUM(G120:AG120) -> 5 | G120: 1 | H120: 0 | I120: 0 | J120: 0 | K120: 0 | L120: 0 | M120: 1 | N120: 1 | O120: 0 | P120: 0 | Q120: 0 | R120: 0 | S120: 0 | T120: 0 | U120: 0 | V120: 0 | W120: 0 | X120: 0 | Y120: 0 | Z120: 1 | AA120: 1 | AB120: 0 | AC120: 0 | AD120: 0 | AE120: 0 | AF120: 0 | AG120: 0
A121: 深圳市龙岗中等专业学校（深圳市龙岗区职业技术学校） | B121: 1-DRF-2817681 | C121: 张岩27 | D121: 教育教学 | E121: 是 | F121: =SUM(G121:AG121) -> 4 | G121: 1 | H121: 0 | I121: 0 | J121: 0 | K121: 0 | L121: 0 | M121: 1 | N121: 0 | O121: 0 | P121: 1 | Q121: 0 | R121: 0 | S121: 0 | T121: 0 | U121: 0 | V121: 0 | W121: 0 | X121: 0 | Y121: 0 | Z121: 0 | AA121: 0 | AB121: 0 | AC121: 0 | AD121: 1 | AE121: 0 | AF121: 0 | AG121: 0
A122: 深圳市福田区劳动技术教育中心（深圳市福田区青少年科技活动中心）（深圳市福田区中小学生综合实践活动教育基地） | B122: 1-1MAOO1I | C122: 张岩27 | D122: 教育教学 | E122: 否 | F122: =SUM(G122:AG122) -> 5 | G122: 1 | H122: 1 | I122: 0 | J122: 0 | K122: 0 | L122: 0 | M122: 1 | N122: 0 | O122: 0 | P122: 0 | Q122: 0 | R122: 0 | S122: 0 | T122: 1 | U122: 0 | V122: 0 | W122: 0 | X122: 0 | Y122: 0 | Z122: 0 | AA122: 0 | AB122: 0 | AC122: 0 | AD122: 1 | AE122: 0 | AF122: 0 | AG122: 0
... A257: 深圳市南山区人民医院 | B257: 1-HQ-1044053 | C257: 黄子懿 | D257: 文体卫 | E257: 否 | F257: =SUM(G257:AG257) -> 0 | G257: 0 | H257: 0 | I257: 0 | J257: 0 | K257: 0 | L257: 0 | M257: 0 | N257: 0 | O257: 0 | P257: 0 | Q257: 0 | R257: 0 | S257: 0 | T257: 0 | U257: 0 | V257: 0 | W257: 0 | X257: 0 | Y257: 0 | Z257: 0 | AA257: 0 | AB257: 0 | AC257: 0 | AD257: 0 | AE257: 0 | AF257: 0 | AG257: 0
A258: 中华人民共和国深圳海关 | B258: 1-2AGTGP | C258: 刘冬6 | D258: =VLOOKUP(C258,[1]销售对应表!$C:$J,5,0) -> 司法行业组 | E258: 是 | F258: =SUM(G258:AG258) -> 20 | G258: 1 | H258: 1 | I258: 1 | J258: 1 | K258: 1 | L258: 1 | M258: 1 | N258: 1 | O258: 1 | P258: 1 | Q258: 1 | R258: 1 | S258: 1 | T258: 0 | U258: 1 | V258: 0 | W258: 0 | X258: 0 | Y258: 0 | Z258: 1 | AA258: 1 | AB258: 1 | AC258: 1 | AD258: 1 | AE258: 0 | AF258: 0 | AG258: 1
A259: 深圳市公安局监所管理支队（深圳市公安局监所管理局） | B259: 1-1PKXN | C259: 刘冬6 | D259: =VLOOKUP(C259,[1]销售对应表!$C:$J,5,0) -> 司法行业组 | E259: 是 | F259: =SUM(G259:AG259) -> 17 | G259: 1 | H259: 0 | I259: 0 | J259: 1 | K259: 1 | L259: 1 | M259: 0 | N259: 1 | O259: 1 | P259: 0 | Q259: 0 | R259: 1 | S259: 1 | T259: 1 | U259: 0 | V259: 1 | W259: 1 | X259: 0 | Y259: 0 | Z259: 0 | AA259: 1 | AB259: 1 | AC259: 1 | AD259: 1 | AE259: 1 | AF259: 0 | AG259: 1
A260: 中广核工程有限公司 | B260: 1-3016627051 | C260: 刘冬6 | D260: =VLOOKUP(C260,[1]销售对应表!$C:$J,5,0) -> 司法行业组 | E260: 是 | F260: =SUM(G260:AG260) -> 13 | G260: 1 | H260: 1 | I260: 0 | J260: 1 | K260: 1 | L260: 0 | M260: 1 | N260: 1 | O260: 0 | P260: 1 | Q260: 1 | R260: 0 | S260: 1 | T260: 0 | U260: 0 | V260: 1 | W260: 0 | X260: 0 | Y260: 0 | Z260: 0 | AA260: 1 | AB260: 1 | AC260: 1 | AD260: 0 | AE260: 0 | AF260: 0 | AG260: 0
A261: 深圳市人民政府口岸办公室 | B261: 1-DRF-2818704 | C261: 刘冬6 | D261: =VLOOKUP(C261,[1]销售对应表!$C:$J,5,0) -> 司法行业组 | E261: 是 | F261: =SUM(G261:AG261) -> 8 | G261: 1 | H261: 1 | I261: 0 | J261: 1 | K261: 0 | L261: 0 | M261: 1 | N261: 1 | O261: 0 | P261: 1 | Q261: 1 | R261: 0 | S261: 0 | T261: 0 | U261: 0 | V261: 0 | W261: 0 | X261: 0 | Y261: 0 | Z261: 0 | AA261: 0 | AB261: 0 | AC261: 0 | AD261: 0 | AE261: 0 | AF261: 0 | AG261: 1
A262: 中华人民共和国深圳出入境边防检查总站 | B262: 1-1KJNAQW | C262: 刘冬6 | D262: =VLOOKUP(C262,[1]销售对应表!$C:$J,5,0) -> 司法行业组 | E262: 是 | F262: =SUM(G262:AG262) -> 8 | G262: 1 | H262: 1 | I262: 0 | J262: 1 | K262: 1 | L262: 0 | M262: 0 | N262: 0 | O262: 0 | P262: 0 | Q262: 0 | R262: 0 | S262: 0 | T262: 1 | U262: 0 | V262: 0 | W262: 0 | X262: 0 | Y262: 0 | Z262: 0 | AA262: 0 | AB262: 1 | AC262: 1 | AD262: 0 | AE262: 0 | AF262: 1 | AG262: 0
A263: 大亚湾核电运营管理有限责任公司 | B263: 1-4XT42X9 | C263: 刘冬6 | D263: =VLOOKUP(C263,[1]销售对应表!$C:$J,5,0) -> 司法行业组 | E263: 是 | F263: =SUM(G263:AG263) -> 5 | G263: 1 | H263: 1 | I263: 0 | J263: 0 | K263: 0 | L263: 0 | M263: 0 | N263: 0 | O263: 0 | P263: 1 | Q263: 0 | R263: 0 | S263: 0 | T263: 1 | U263: 0 | V263: 0 | W263: 0 | X263: 0 | Y263: 0 | Z263: 0 | AA263: 1 | AB263: 0 | AC263: 0 | AD263: 0 | AE263: 0 | AF263: 0 | AG263: 0
A264: 广东省深圳监狱 | B264: 1-C7MR6I | C264: 刘冬6 | D264: =VLOOKUP(C264,[1]销售对应表!$C:$J,5,0) -> 司法行业组 | E264: 否 | F264: =SUM(G264:AG264) -> 3 | G264: 0 | H264: 0 | I264: 0 | J264: 0 | K264: 0 | L264: 0 | M264: 1 | N264: 0 | O264: 0 | P264: 0 | Q264: 0 | R264: 0 | S264: 0 | T264: 1 | U264: 1 | V264: 0 | W264: 0 | X264: 0 | Y264: 0 | Z264: 0 | AA264: 0 | AB264: 0 | AC264: 0 | AD264: 0 | AE264: 0 | AF264: 0 | AG264: 0
A265: 中广核服务集团有限公司 | B265: 1-DRFT-2987017 | C265: 刘冬6 | D265: =VLOOKUP(C265,[1]销售对应表!$C:$J,5,0) -> 司法行业组 | E265: 否 | F265: =SUM(G265:AG265) -> 4 | G265: 1 | H265: 0 | I265: 0 | J265: 0 | K265: 0 | L265: 0 | M265: 0 | N265: 0 | O265: 0 | P265: 1 | Q265: 0 | R265: 1 | S265: 0 | T265: 0 | U265: 0 | V265: 0 | W265: 0 | X265: 0 | Y265: 0 | Z265: 1 | AA265: 0 | AB265: 0 | AC265: 0 | AD265: 0 | AE265: 0 | AF265: 0 | AG265: 0
A266: 深圳海关缉私局 | B266: 1-1DL948V | C266: 刘冬6 | D266: =VLOOKUP(C266,[1]销售对应表!$C:$J,5,0) -> 司法行业组 | E266: 否 | F266: =SUM(G266:AG266) -> 3 | G266: 1 | H266: 0 | I266: 0 | J266: 0 | K266: 0 | L266: 0 | M266: 1 | N266: 0 | O266: 0 | P266: 0 | Q266: 0 | R266: 0 | S266: 0 | T266: 0 | U266: 0 | V266: 0 | W266: 1 | X266: 0 | Y266: 0 | Z266: 0 | AA266: 0 | AB266: 0 | AC266: 0 | AD266: 0 | AE266: 0 | AF266: 0 | AG266: 0
A267: 中国人民解放军驻香港部队 | B267: 1-DRF-2813005 | C267: 刘冬6 | D267: =VLOOKUP(C267,[1]销售对应表!$C:$J,5,0) -> 司法行业组 | E267: 否 | F267: =SUM(G267:AG267) -> 3 | G267: 1 | H267: 1 | I267: 0 | J267: 0 | K267: 0 | L267: 0 | M267: 1 | N267: 0 | O267: 0 | P267: 0 | Q267: 0 | R267: 0 | S267: 0 | T267: 0 | U267: 0 | V267: 0 | W267: 0 | X267: 0 | Y267: 0 | Z267: 0 | AA267: 0 | AB267: 0 | AC267: 0 | AD267: 0 | AE267: 0 | AF267: 0 | AG267: 0
A268: 深圳市机场国际快件海关监管中心有限公司 | B268: 1-5QJLLDP | C268: 刘冬6 | D268: =VLOOKUP(C268,[1]销售对应表!$C:$J,5,0) -> 司法行业组 | E268: 否 | F268: =SUM(G268:AG268) -> 2 | G268: 1 | H268: 0 | I268: 0 | J268: 0 | K268: 0 | L268: 0 | M268: 0 | N268: 0 | O268: 0 | P268: 0 | Q268: 0 | R268: 0 | S268: 1 | T268: 0 | U268: 0 | V268: 0 | W268: 0 | X268: 0 | Y268: 0 | Z268: 0 | AA268: 0 | AB268: 0 | AC268: 0 | AD268: 0 | AE268: 0 | AF268: 0 | AG268: 0
A269: 深圳市司法局 | B269: 1-DRF-2823328 | C269: 刘冬6 | D269: =VLOOKUP(C269,[1]销售对应表!$C:$J,5,0) -> 司法行业组 | E269: 否 | F269: =SUM(G269:AG269) -> 2 | G269: 0 | H269: 0 | I269: 0 | J269: 1 | K269: 0 | L269: 0 | M269: 0 | N269: 0 | O269: 0 | P269: 0 | Q269: 0 | R269: 1 | S269: 0 | T269: 0 | U269: 0 | V269: 0 | W269: 0 | X269: 0 | Y269: 0 | Z269: 0 | AA269: 0 | AB269: 0 | AC269: 0 | AD269: 0 | AE269: 0 | AF269: 0 | AG269: 0
... A339: 深圳市交通运输局坪山管理局 | B339: 1-2UK6OVV | C339: 王魁8 | D339: =VLOOKUP(C339,[1]销售对应表!$C:$J,5,0) -> 交通行业组 | E339: 否 | F339: =SUM(G339:AG339) -> 0 | G339: 0 | H339: 0 | I339: 0 | J339: 0 | K339: 0 | L339: 0 | M339: 0 | N339: 0 | O339: 0 | P339: 0 | Q339: 0 | R339: 0 | S339: 0 | T339: 0 | U339: 0 | V339: 0 | W339: 0 | X339: 0 | Y339: 0 | Z339: 0 | AA339: 0 | AB339: 0 | AC339: 0 | AD339: 0 | AE339: 0 | AF339: 0 | AG339: 0
A340: 广东粤海水务股份有限公司 | B340: 1-20H8XC8 | C340: 林若驹 | D340: 行业二部-水务 | E340: 是 | F340: =SUM(G340:AG340) -> 17 | G340: 1 | H340: 1 | I340: 1 | J340: 1 | K340: 1 | L340: 0 | M340: 1 | N340: 1 | O340: 1 | P340: 0 | Q340: 0 | R340: 1 | S340: 1 | T340: 1 | U340: 1 | V340: 0 | W340: 1 | X340: 1 | Y340: 0 | Z340: 0 | AA340: 1 | AB340: 0 | AC340: 1 | AD340: 1 | AE340: 0 | AF340: 0 | AG340: 0
A341: 深圳市水务（集团）有限公司 | B341: 1-DRF-2815277 | C341: 林若驹 | D341: 行业二部-水务 | E341: 是 | F341: =SUM(G341:AG341) -> 17 | G341: 1 | H341: 1 | I341: 1 | J341: 1 | K341: 1 | L341: 1 | M341: 1 | N341: 1 | O341: 0 | P341: 0 | Q341: 0 | R341: 1 | S341: 1 | T341: 1 | U341: 1 | V341: 0 | W341: 1 | X341: 1 | Y341: 0 | Z341: 0 | AA341: 1 | AB341: 0 | AC341: 1 | AD341: 0 | AE341: 1 | AF341: 0 | AG341: 0
A342: 深圳市水务局 | B342: 1-3GDP9 | C342: 林若驹 | D342: 行业二部-水务 | E342: 是 | F342: =SUM(G342:AG342) -> 8 | G342: 1 | H342: 1 | I342: 1 | J342: 0 | K342: 0 | L342: 0 | M342: 1 | N342: 0 | O342: 0 | P342: 1 | Q342: 0 | R342: 0 | S342: 0 | T342: 1 | U342: 0 | V342: 0 | W342: 0 | X342: 0 | Y342: 0 | Z342: 0 | AA342: 0 | AB342: 1 | AC342: 0 | AD342: 1 | AE342: 0 | AF342: 0 | AG342: 0
A343: 深圳市大鹏新区水务局 | B343: 1-5BMQ65P | C343: 林若驹 | D343: 行业二部-水务 | E343: 是 | F343: =SUM(G343:AG343) -> 7 | G343: 1 | H343: 1 | I343: 0 | J343: 0 | K343: 1 | L343: 0 | M343: 1 | N343: 0 | O343: 0 | P343: 1 | Q343: 0 | R343: 0 | S343: 0 | T343: 0 | U343: 0 | V343: 0 | W343: 0 | X343: 0 | Y343: 0 | Z343: 0 | AA343: 0 | AB343: 0 | AC343: 0 | AD343: 0 | AE343: 1 | AF343: 0 | AG343: 1
A344: 深圳市龙岗区水务局 | B344: 1-DRF-2813185 | C344: 林若驹 | D344: 行业二部-水务 | E344: 是 | F344: =SUM(G344:AG344) -> 8 | G344: 1 | H344: 1 | I344: 0 | J344: 0 | K344: 0 | L344: 0 | M344: 1 | N344: 0 | O344: 0 | P344: 0 | Q344: 0 | R344: 0 | S344: 0 | T344: 1 | U344: 1 | V344: 0 | W344: 1 | X344: 0 | Y344: 0 | Z344: 0 | AA344: 0 | AB344: 1 | AC344: 0 | AD344: 1 | AE344: 0 | AF344: 0 | AG344: 0
A345: 深圳市坪山区水务局 | B345: 1-37D1GZY | C345: 林若驹 | D345: 行业二部-水务 | E345: 否 | F345: =SUM(G345:AG345) -> 6 | G345: 0 | H345: 1 | I345: 0 | J345: 0 | K345: 0 | L345: 0 | M345: 1 | N345: 0 | O345: 0 | P345: 0 | Q345: 0 | R345: 0 | S345: 0 | T345: 1 | U345: 1 | V345: 0 | W345: 1 | X345: 0 | Y345: 0 | Z345: 0 | AA345: 0 | AB345: 0 | AC345: 0 | AD345: 1 | AE345: 0 | AF345: 0 | AG345: 0
A346: 深圳市深水宝安水务集团有限公司 | B346: 1-1W9WLFJ | C346: 林若驹 | D346: 行业二部-水务 | E346: 是 | F346: =SUM(G346:AG346) -> 6 | G346: 0 | H346: 0 | I346: 0 | J346: 0 | K346: 0 | L346: 0 | M346: 0 | N346: 0 | O346: 0 | P346: 0 | Q346: 0 | R346: 0 | S346: 0 | T346: 1 | U346: 1 | V346: 0 | W346: 1 | X346: 0 | Y346: 0 | Z346: 0 | AA346: 1 | AB346: 1 | AC346: 0 | AD346: 1 | AE346: 0 | AF346: 0 | AG346: 0
A347: 广东粤港供水有限公司 | B347: 1-DRF-2814164 | C347: 林若驹 | D347: 行业二部-水务 | E347: 否 | F347: =SUM(G347:AG347) -> 5 | G347: 1 | H347: 1 | I347: 0 | J347: 0 | K347: 0 | L347: 0 | M347: 1 | N347: 0 | O347: 0 | P347: 0 | Q347: 0 | R347: 0 | S347: 0 | T347: 1 | U347: 0 | V347: 0 | W347: 0 | X347: 0 | Y347: 0 | Z347: 0 | AA347: 1 | AB347: 0 | AC347: 0 | AD347: 0 | AE347: 0 | AF347: 0 | AG347: 0
A348: 深圳市深水龙岗水务集团有限公司 | B348: 1-4UCNTLL | C348: 林若驹 | D348: 行业二部-水务 | E348: 是 | F348: =SUM(G348:AG348) -> 4 | G348: 0 | H348: 0 | I348: 0 | J348: 0 | K348: 1 | L348: 0 | M348: 1 | N348: 0 | O348: 0 | P348: 1 | Q348: 0 | R348: 0 | S348: 0 | T348: 1 | U348: 0 | V348: 0 | W348: 0 | X348: 0 | Y348: 0 | Z348: 0 | AA348: 0 | AB348: 0 | AC348: 0 | AD348: 0 | AE348: 0 | AF348: 0 | AG348: 0
A349: 深圳市宝安区水务局 | B349: 1-1P51DO5 | C349: 林若驹 | D349: 行业二部-水务 | E349: 否 | F349: =SUM(G349:AG349) -> 3 | G349: 0 | H349: 1 | I349: 0 | J349: 0 | K349: 0 | L349: 1 | M349: 0 | N349: 0 | O349: 0 | P349: 1 | Q349: 0 | R349: 0 | S349: 0 | T349: 0 | U349: 0 | V349: 0 | W349: 0 | X349: 0 | Y349: 0 | Z349: 0 | AA349: 0 | AB349: 0 | AC349: 0 | AD349: 0 | AE349: 0 | AF349: 0 | AG349: 0
A350: 深圳市光明区水务局 | B350: 1-39Q2E19 | C350: 林若驹 | D350: 行业二部-水务 | E350: 否 | F350: =SUM(G350:AG350) -> 3 | G350: 1 | H350: 0 | I350: 0 | J350: 0 | K350: 0 | L350: 0 | M350: 1 | N350: 0 | O350: 0 | P350: 1 | Q350: 0 | R350: 0 | S350: 0 | T350: 0 | U350: 0 | V350: 0 | W350: 0 | X350: 0 | Y350: 0 | Z350: 0 | AA350: 0 | AB350: 0 | AC350: 0 | AD350: 0 | AE350: 0 | AF350: 0 | AG350: 0
A351: 深圳市龙华区水务局 | B351: 1-39JOHHK | C351: 林若驹 | D351: 行业二部-水务 | E351: 是 | F351: =SUM(G351:AG351) -> 2 | G351: 1 | H351: 1 | I351: 0 | J351: 0 | K351: 0 | L351: 0 | M351: 0 | N351: 0 | O351: 0 | P351: 0 | Q351: 0 | R351: 0 | S351: 0 | T351: 0 | U351: 0 | V351: 0 | W351: 0 | X351: 0 | Y351: 0 | Z351: 0 | AA351: 0 | AB351: 0 | AC351: 0 | AD351: 0 | AE351: 0 | AF351: 0 | AG351: 0
... A357: 深圳市盐田区水务局 | B357: 1-25N2819 | C357: 林若驹 | D357: 行业二部-水务 | E357: 否 | F357: =SUM(G357:AG357) -> 0 | G357: 0 | H357: 0 | I357: 0 | J357: 0 | K357: 0 | L357: 0 | M357: 0 | N357: 0 | O357: 0 | P357: 0 | Q357: 0 | R357: 0 | S357: 0 | T357: 0 | U357: 0 | V357: 0 | W357: 0 | X357: 0 | Y357: 0 | Z357: 0 | AA357: 0 | AB357: 0 | AC357: 0 | AD357: 0 | AE357: 0 | AF357: 0 | AG357: 0
A358: 深圳市公安局交通警察支队南山大队 | B358: 1-1E3DCD5 | C358: 张腾辉6 | D358: =VLOOKUP(C358,[1]销售对应表!$C:$J,5,0) -> 公安交警行业组 | E358: 是 | F358: =SUM(G358:AG358) -> 7 | G358: 1 | H358: 1 | I358: 0 | J358: 1 | K358: 0 | L358: 0 | M358: 1 | N358: 0 | O358: 0 | P358: 0 | Q358: 1 | R358: 0 | S358: 0 | T358: 1 | U358: 0 | V358: 0 | W358: 0 | X358: 0 | Y358: 0 | Z358: 0 | AA358: 0 | AB358: 0 | AC358: 0 | AD358: 0 | AE358: 0 | AF358: 1 | AG358: 0
A359: 深圳市公安局深汕特别合作区分局 | B359: 1-3G2KGPC | C359: 张腾辉6 | D359: =VLOOKUP(C359,[1]销售对应表!$C:$J,5,0) -> 公安交警行业组 | E359: 是 | F359: =SUM(G359:AG359) -> 8 | G359: 1 | H359: 0 | I359: 0 | J359: 0 | K359: 1 | L359: 1 | M359: 1 | N359: 1 | O359: 0 | P359: 1 | Q359: 0 | R359: 0 | S359: 0 | T359: 0 | U359: 0 | V359: 0 | W359: 0 | X359: 0 | Y359: 0 | Z359: 0 | AA359: 0 | AB359: 0 | AC359: 0 | AD359: 0 | AE359: 1 | AF359: 0 | AG359: 1
A360: 深圳市公安局福田分局 | B360: 1-1PKPF | C360: 张腾辉6 | D360: =VLOOKUP(C360,[1]销售对应表!$C:$J,5,0) -> 公安交警行业组 | E360: 是 | F360: =SUM(G360:AG360) -> 7 | G360: 1 | H360: 1 | I360: 0 | J360: 1 | K360: 0 | L360: 0 | M360: 0 | N360: 0 | O360: 0 | P360: 1 | Q360: 0 | R360: 0 | S360: 0 | T360: 1 | U360: 0 | V360: 0 | W360: 0 | X360: 0 | Y360: 1 | Z360: 0 | AA360: 1 | AB360: 0 | AC360: 0 | AD360: 0 | AE360: 0 | AF360: 0 | AG360: 0
A361: 深圳市公安局交通管理支队车辆管理大队（深圳市公安局交通管理支队车辆管理所） | B361: 1-1LJCCDX | C361: 张腾辉6 | D361: =VLOOKUP(C361,[1]销售对应表!$C:$J,5,0) -> 公安交警行业组 | E361: 是 | F361: =SUM(G361:AG361) -> 5 | G361: 1 | H361: 0 | I361: 0 | J361: 1 | K361: 0 | L361: 0 | M361: 0 | N361: 0 | O361: 0 | P361: 1 | Q361: 0 | R361: 0 | S361: 0 | T361: 0 | U361: 0 | V361: 0 | W361: 1 | X361: 0 | Y361: 0 | Z361: 0 | AA361: 1 | AB361: 0 | AC361: 0 | AD361: 0 | AE361: 0 | AF361: 0 | AG361: 0
A362: 深圳市公安局交通管理支队罗湖大队 | B362: 1-1MXF6F6 | C362: 张腾辉6 | D362: =VLOOKUP(C362,[1]销售对应表!$C:$J,5,0) -> 公安交警行业组 | E362: 是 | F362: =SUM(G362:AG362) -> 6 | G362: 1 | H362: 1 | I362: 0 | J362: 0 | K362: 1 | L362: 0 | M362: 0 | N362: 0 | O362: 0 | P362: 0 | Q362: 1 | R362: 0 | S362: 0 | T362: 0 | U362: 0 | V362: 0 | W362: 0 | X362: 1 | Y362: 0 | Z362: 0 | AA362: 0 | AB362: 0 | AC362: 0 | AD362: 0 | AE362: 1 | AF362: 0 | AG362: 0
A363: 深圳市公安局交通警察支队福田大队 | B363: 1-1MX348N | C363: 张腾辉6 | D363: =VLOOKUP(C363,[1]销售对应表!$C:$J,5,0) -> 公安交警行业组 | E363: 是 | F363: =SUM(G363:AG363) -> 6 | G363: 1 | H363: 1 | I363: 0 | J363: 0 | K363: 0 | L363: 0 | M363: 0 | N363: 0 | O363: 0 | P363: 0 | Q363: 1 | R363: 1 | S363: 0 | T363: 1 | U363: 0 | V363: 0 | W363: 0 | X363: 0 | Y363: 0 | Z363: 0 | AA363: 0 | AB363: 0 | AC363: 0 | AD363: 1 | AE363: 0 | AF363: 0 | AG363: 0
A364: 深圳市公安局南山分局 | B364: 1-1PKSH | C364: 张腾辉6 | D364: =VLOOKUP(C364,[1]销售对应表!$C:$J,5,0) -> 公安交警行业组 | E364: 是 | F364: =SUM(G364:AG364) -> 5 | G364: 1 | H364: 1 | I364: 0 | J364: 0 | K364: 1 | L364: 0 | M364: 1 | N364: 0 | O364: 0 | P364: 0 | Q364: 0 | R364: 0 | S364: 0 | T364: 1 | U364: 0 | V364: 0 | W364: 0 | X364: 0 | Y364: 0 | Z364: 0 | AA364: 0 | AB364: 0 | AC364: 0 | AD364: 0 | AE364: 0 | AF364: 0 | AG364: 0
A365: 深圳市公安局交通警察支队坪山大队 | B365: 1-DRF-2814585 | C365: 张腾辉6 | D365: =VLOOKUP(C365,[1]销售对应表!$C:$J,5,0) -> 公安交警行业组 | E365: 是 | F365: =SUM(G365:AG365) -> 3 | G365: 1 | H365: 1 | I365: 0 | J365: 0 | K365: 0 | L365: 0 | M365: 0 | N365: 0 | O365: 0 | P365: 0 | Q365: 1 | R365: 0 | S365: 0 | T365: 0 | U365: 0 | V365: 0 | W365: 0 | X365: 0 | Y365: 0 | Z365: 0 | AA365: 0 | AB365: 0 | AC365: 0 | AD365: 0 | AE365: 0 | AF365: 0 | AG365: 0
A366: 深圳市公安局交通警察支队侦查大队（事故处理大队） | B366: 1-1OL9YSC | C366: 张腾辉6 | D366: =VLOOKUP(C366,[1]销售对应表!$C:$J,5,0) -> 公安交警行业组 | E366: 是 | F366: =SUM(G366:AG366) -> 4 | G366: 1 | H366: 0 | I366: 0 | J366: 0 | K366: 0 | L366: 0 | M366: 0 | N366: 1 | O366: 0 | P366: 0 | Q366: 1 | R366: 0 | S366: 0 | T366: 0 | U366: 0 | V366: 0 | W366: 0 | X366: 0 | Y366: 0 | Z366: 0 | AA366: 0 | AB366: 1 | AC366: 0 | AD366: 0 | AE366: 0 | AF366: 0 | AG366: 0
A367: 深圳市公安局罗湖分局 | B367: 1-1PKQ2 | C367: 张腾辉6 | D367: =VLOOKUP(C367,[1]销售对应表!$C:$J,5,0) -> 公安交警行业组 | E367: 否 | F367: =SUM(G367:AG367) -> 3 | G367: 0 | H367: 0 | I367: 1 | J367: 0 | K367: 0 | L367: 0 | M367: 0 | N367: 0 | O367: 0 | P367: 0 | Q367: 1 | R367: 0 | S367: 0 | T367: 1 | U367: 0 | V367: 0 | W367: 0 | X367: 0 | Y367: 0 | Z367: 0 | AA367: 0 | AB367: 0 | AC367: 0 | AD367: 0 | AE367: 0 | AF367: 0 | AG367: 0
A368: 中共深圳市委政法委员会 | B368: 1-3EV3O34 | C368: 张腾辉6 | D368: =VLOOKUP(C368,[1]销售对应表!$C:$J,5,0) -> 公安交警行业组 | E368: 否 | F368: =SUM(G368:AG368) -> 1 | G368: 0 | H368: 0 | I368: 0 | J368: 0 | K368: 1 | L368: 0 | M368: 0 | N368: 0 | O368: 0 | P368: 0 | Q368: 0 | R368: 0 | S368: 0 | T368: 0 | U368: 0 | V368: 0 | W368: 0 | X368: 0 | Y368: 0 | Z368: 0 | AA368: 0 | AB368: 0 | AC368: 0 | AD368: 0 | AE368: 0 | AF368: 0 | AG368: 0
A369: 深圳市公安局交通管理支队西部高速公路大队 | B369: 1-4HQPVX9 | C369: 张腾辉6 | D369: =VLOOKUP(C369,[1]销售对应表!$C:$J,5,0) -> 公安交警行业组 | E369: 否 | F369: =SUM(G369:AG369) -> 1 | G369: 1 | H369: 0 | I369: 0 | J369: 0 | K369: 0 | L369: 0 | M369: 0 | N369: 0 | O369: 0 | P369: 0 | Q369: 0 | R369: 0 | S369: 0 | T369: 0 | U369: 0 | V369: 0 | W369: 0 | X369: 0 | Y369: 0 | Z369: 0 | AA369: 0 | AB369: 0 | AC369: 0 | AD369: 0 | AE369: 0 | AF369: 0 | AG369: 0
... A396: 深圳市公安局特警支队 | B396: 1-1YJGQZ5 | C396: 郭庆3 | D396: =VLOOKUP(C396,[1]销售对应表!$C:$J,5,0) -> 公安交警行业组 | E396: 否 | F396: =SUM(G396:AG396) -> 1 | G396: 0 | H396: 0 | I396: 0 | J396: 0 | K396: 0 | L396: 0 | M396: 0 | N396: 0 | O396: 0 | P396: 0 | Q396: 0 | R396: 0 | S396: 0 | T396: 1 | U396: 0 | V396: 0 | W396: 0 | X396: 0 | Y396: 0 | Z396: 0 | AA396: 0 | AB396: 0 | AC396: 0 | AD396: 0 | AE396: 0 | AF396: 0 | AG396: 0
